agentd/__init__.py
agentd/app.py
agentd/eval.py
agentd/mcp_bridge.py
agentd/microsandbox_cli_executor.py
agentd/microsandbox_executor.py
agentd/patch.py
agentd/ptc.py
agentd/sandbox_runtime_executor.py
agentd/tool_decorator.py
agentd/model/__init__.py
agentd/model/config.py
agentd-0.3.3.dist-info/METADATA
agentd-0.3.3.dist-info/WHEEL
agentd-0.3.3.dist-info/entry_points.txt
agentd-0.3.3.dist-info/licenses/LICENSE
agentd-0.3.3.dist-info/RECORD
