Metadata-Version: 2.4
Name: agentd
Version: 0.3.3
Summary: agent daemon
License-File: LICENSE
Requires-Python: >=3.10
Requires-Dist: httpx>=0.27.0
Requires-Dist: litellm>=1.80.0
Requires-Dist: mcp-subscribe
Requires-Dist: mcp>=1.25.0
Requires-Dist: openai-agents>=0.6.4
Requires-Dist: openai>=1.76.0
Requires-Dist: pyyaml>=6.0.2
